{"v":"5.6.10","fr":29.9700012207031,"ip":0,"op":150.000006109625,"w":1080,"h":1080,"nm":"poodle","ddd":0,"assets":[{"id":"comp_0","layers":[{"ddd":0,"ind":1,"ty":4,"nm":"luoi Outlines","sr":1,"ks":{"o":{"a":0,"k":100,"ix":11},"r":{"a":0,"k":0,"ix":10},"p":{"a":1,"k":[{"i":{"x":0.667,"y":1},"o":{"x":0.333,"y":0},"t":0,"s":[540.214,459.046,0],"to":[-1.333,-3.5,0],"ti":[0,0,0]},{"i":{"x":0.667,"y":1},"o":{"x":0.333,"y":0},"t":9.888,"s":[532.214,438.046,0],"to":[0,0,0],"ti":[0,0,0]},{"i":{"x":0.667,"y":1},"o":{"x":0.333,"y":0},"t":20.171,"s":[540.214,459.046,0],"to":[0,0,0],"ti":[0,0,0]},{"i":{"x":0.667,"y":1},"o":{"x":0.333,"y":0},"t":30.059,"s":[532.214,438.046,0],"to":[0,0,0],"ti":[0,0,0]},{"i":{"x":0.667,"y":1},"o":{"x":0.333,"y":0},"t":39.946,"s":[540.214,459.046,0],"to":[0,0,0],"ti":[0,0,0]},{"i":{"x":0.667,"y":1},"o":{"x":0.333,"y":0},"t":49.834,"s":[532.214,438.046,0],"to":[0,0,0],"ti":[0,0,0]},{"i":{"x":0.667,"y":1},"o":{"x":0.167,"y":0},"t":59.593,"s":[540.214,459.046,0],"to":[0,0,0],"ti":[0,0,0]},{"i":{"x":0.667,"y":1},"o":{"x":0.333,"y":0},"t":70.519,"s":[532.214,438.046,0],"to":[0,0,0],"ti":[0,0,0]},{"i":{"x":0.667,"y":1},"o":{"x":0.333,"y":0},"t":80.803,"s":[540.214,459.046,0],"to":[0,0,0],"ti":[0,0,0]},{"i":{"x":0.667,"y":1},"o":{"x":0.333,"y":0},"t":90.69,"s":[532.214,438.046,0],"to":[0,0,0],"ti":[0,0,0]},{"i":{"x":0.667,"y":1},"o":{"x":0.333,"y":0},"t":100.578,"s":[540.214,459.046,0],"to":[0,0,0],"ti":[0,0,0]},{"i":{"x":0.667,"y":1},"o":{"x":0.333,"y":0},"t":110.465,"s":[532.214,438.046,0],"to":[0,0,0],"ti":[0,0,0]},{"i":{"x":0.667,"y":1},"o":{"x":0.167,"y":0},"t":120.225,"s":[540.214,459.046,0],"to":[0,0,0],"ti":[0,0,0]},{"i":{"x":0.667,"y":1},"o":{"x":0.333,"y":0},"t":130.113,"s":[532.214,438.046,0],"to":[0,0,0],"ti":[0,0,0]},{"i":{"x":0.667,"y":1},"o":{"x":0.333,"y":0},"t":140,"s":[540.214,459.046,0],"to":[0,0,0],"ti":[1.333,3.5,0]},{"t":149.000006068894,"s":[532.214,438.046,0]}],"ix":2},"a":{"a":0,"k":[32.417,5.313,0],"ix":1},"s":{"a":0,"k":[100,100,100],"ix":6}},"ao":0,"sy":[{"c":{"a":0,"k":[0,0,0,1],"ix":2},"o":{"a":0,"k":75,"ix":3},"a":{"a":0,"k":120,"ix":5},"s":{"a":0,"k":5,"ix":8},"d":{"a":0,"k":5,"ix":6},"ch":{"a":0,"k":0,"ix":7},"bm":{"a":0,"k":5,"ix":1},"no":{"a":0,"k":0,"ix":9},"lc":{"a":0,"k":1,"ix":10},"ty":1,"nm":"Drop Shadow"},{"c":{"a":0,"k":[0,0,0,1],"ix":2},"o":{"a":0,"k":75,"ix":3},"a":{"a":0,"k":120,"ix":5},"s":{"a":0,"k":5,"ix":8},"d":{"a":0,"k":5,"ix":6},"ch":{"a":0,"k":0,"ix":7},"bm":{"a":0,"k":5,"ix":1},"no":{"a":0,"k":0,"ix":9},"ty":2,"nm":"Inner Shadow"},{"c":{"a":0,"k":[1,1,0.745098039216,1],"ix":5},"o":{"a":0,"k":75,"ix":2},"s":{"a":0,"k":5,"ix":10},"r":{"a":0,"k":50,"ix":11},"ch":{"a":0,"k":0,"ix":9},"bm":{"a":0,"k":11,"ix":1},"no":{"a":0,"k":0,"ix":3},"j":{"a":0,"k":0,"ix":12},"ty":3,"nm":"Outer Glow"},{"c":{"a":0,"k":[1,1,0.745098039216,1],"ix":5},"o":{"a":0,"k":75,"ix":2},"s":{"a":0,"k":5,"ix":11},"r":{"a":0,"k":50,"ix":12},"sr":{"a":0,"k":1,"ix":9},"ch":{"a":0,"k":0,"ix":10},"bm":{"a":0,"k":11,"ix":1},"no":{"a":0,"k":0,"ix":3},"j":{"a":0,"k":0,"ix":13},"ty":4,"nm":"Inner Glow"},{"c":{"a":0,"k":[1,0,0,1],"ix":2},"s":{"a":0,"k":3,"ix":3},"ty":0,"nm":"Stroke"}],"shapes":[{"ty":"gr","it":[{"ind":0,"ty":"sh","ix":1,"ks":{"a":0,"k":{"i":[[0,0],[0,0],[1.136,-0.442],[0.706,1.812],[0,0]],"o":[[0,0],[0.68,1.745],[-1.179,0.46],[0,0],[0,0]],"v":[[-9.561,-31.341],[13.435,27.194],[12.593,31.232],[9.198,28.844],[-13.772,-29.624]],"c":true},"ix":2},"nm":"Path 1","mn":"ADBE Vector Shape - Group","hd":false},{"ty":"fl","c":{"a":0,"k":[0.910000011968,0.375999989229,0.231000010173,1],"ix":4},"o":{"a":0,"k":100,"ix":5},"r":1,"bm":0,"nm":"Fill 1","mn":"ADBE Vector Graphic - Fill","hd":false},{"ty":"tr","p":{"a":0,"k":[43.431,34.401],"ix":2},"a":{"a":0,"k":[0,0],"ix":1},"s":{"a":0,"k":[100,100],"ix":3},"r":{"a":0,"k":0,"ix":6},"o":{"a":0,"k":100,"ix":7},"sk":{"a":0,"k":0,"ix":4},"sa":{"a":0,"k":0,"ix":5},"nm":"Transform"}],"nm":"Group 1","np":4,"cix":2,"bm":0,"ix":1,"mn":"ADBE Vector Group","hd":false},{"ty":"gr","it":[{"ind":0,"ty":"sh","ix":1,"ks":{"a":0,"k":{"i":[[0,0],[0,0],[0,0],[0,0],[0,0],[-28.169,-25.443],[-7.496,4.389],[-1.525,16.364]],"o":[[0,0],[0,0],[0,0],[0,0],[0,0],[12.19,11.022],[8.49,-1.836],[3.542,-37.793]],"v":[[25.485,-53.814],[13.502,-52.935],[-14.306,-50.841],[-36.248,-33.56],[-45.667,-26.104],[-5.004,42.792],[24.699,49.313],[42.126,24.438]],"c":true},"ix":2},"nm":"Path 1","mn":"ADBE Vector Shape - Group","hd":false},{"ty":"fl","c":{"a":0,"k":[0.976000019148,0.752999997606,0.717999985639,1],"ix":4},"o":{"a":0,"k":100,"ix":5},"r":1,"bm":0,"nm":"Fill 1","mn":"ADBE Vector Graphic - Fill","hd":false},{"ty":"tr","p":{"a":0,"k":[45.917,54.064],"ix":2},"a":{"a":0,"k":[0,0],"ix":1},"s":{"a":0,"k":[100,100],"ix":3},"r":{"a":0,"k":0,"ix":6},"o":{"a":0,"k":100,"ix":7},"sk":{"a":0,"k":0,"ix":4},"sa":{"a":0,"k":0,"ix":5},"nm":"Transform"}],"nm":"Group 2","np":4,"cix":2,"bm":0,"ix":2,"mn":"ADBE Vector Group","hd":false}],"ip":0,"op":150.000006109625,"st":0,"bm":0}]}],"layers":[{"ddd":0,"ind":1,"ty":4,"nm":"chan vay Outlines","parent":6,"sr":1,"ks":{"o":{"a":0,"k":100,"ix":11},"r":{"a":1,"k":[{"i":{"x":[0.667],"y":[1]},"o":{"x":[0.333],"y":[0]},"t":0,"s":[0]},{"i":{"x":[0.667],"y":[1]},"o":{"x":[0.333],"y":[0]},"t":25.369,"s":[15]},{"i":{"x":[0.667],"y":[1]},"o":{"x":[0.333],"y":[0]},"t":50.739,"s":[0]},{"i":{"x":[0.667],"y":[1]},"o":{"x":[0.333],"y":[0]},"t":76.108,"s":[15]},{"i":{"x":[0.667],"y":[1]},"o":{"x":[0.333],"y":[0]},"t":101.476,"s":[0]},{"i":{"x":[0.667],"y":[1]},"o":{"x":[0.333],"y":[0]},"t":126,"s":[15]},{"t":149.000006068894,"s":[0]}],"ix":10},"p":{"a":0,"k":[552.438,211.593,0],"ix":2},"a":{"a":0,"k":[61.184,261.57,0],"ix":1},"s":{"a":0,"k":[100,100,100],"ix":6}},"ao":0,"sy":[{"c":{"a":0,"k":[0,0,0,1],"ix":2},"o":{"a":0,"k":75,"ix":3},"a":{"a":0,"k":120,"ix":5},"s":{"a":0,"k":5,"ix":8},"d":{"a":0,"k":5,"ix":6},"ch":{"a":0,"k":0,"ix":7},"bm":{"a":0,"k":5,"ix":1},"no":{"a":0,"k":0,"ix":9},"lc":{"a":0,"k":1,"ix":10},"ty":1,"nm":"Drop Shadow"},{"c":{"a":0,"k":[0,0,0,1],"ix":2},"o":{"a":0,"k":75,"ix":3},"a":{"a":0,"k":120,"ix":5},"s":{"a":0,"k":5,"ix":8},"d":{"a":0,"k":5,"ix":6},"ch":{"a":0,"k":0,"ix":7},"bm":{"a":0,"k":5,"ix":1},"no":{"a":0,"k":0,"ix":9},"ty":2,"nm":"Inner Shadow"},{"c":{"a":0,"k":[1,1,0.745098039216,1],"ix":5},"o":{"a":0,"k":75,"ix":2},"s":{"a":0,"k":5,"ix":10},"r":{"a":0,"k":50,"ix":11},"ch":{"a":0,"k":0,"ix":9},"bm":{"a":0,"k":11,"ix":1},"no":{"a":0,"k":0,"ix":3},"j":{"a":0,"k":0,"ix":12},"ty":3,"nm":"Outer Glow"},{"c":{"a":0,"k":[1,1,0.745098039216,1],"ix":5},"o":{"a":0,"k":75,"ix":2},"s":{"a":0,"k":5,"ix":11},"r":{"a":0,"k":50,"ix":12},"sr":{"a":0,"k":1,"ix":9},"ch":{"a":0,"k":0,"ix":10},"bm":{"a":0,"k":11,"ix":1},"no":{"a":0,"k":0,"ix":3},"j":{"a":0,"k":0,"ix":13},"ty":4,"nm":"Inner Glow"},{"c":{"a":0,"k":[1,0,0,1],"ix":2},"s":{"a":0,"k":3,"ix":3},"ty":0,"nm":"Stroke"}],"shapes":[{"ty":"gr","it":[{"ind":0,"ty":"sh","ix":1,"ks":{"a":0,"k":{"i":[[8.667,-0.034],[-1.353,15.877],[-8.667,0.034],[1.353,-15.878]],"o":[[-8.668,0.034],[1.353,-15.879],[8.668,-0.034],[-1.354,15.878]],"v":[[-2.45,28.749],[-15.694,0.063],[2.449,-28.75],[15.694,-0.062]],"c":true},"ix":2},"nm":"Path 1","mn":"ADBE Vector Shape - Group","hd":false},{"ty":"fl","c":{"a":0,"k":[0.204000001795,0.081999999402,0.136999990426,1],"ix":4},"o":{"a":0,"k":100,"ix":5},"r":1,"bm":0,"nm":"Fill 1","mn":"ADBE Vector Graphic - Fill","hd":false},{"ty":"tr","p":{"a":0,"k":[93.496,107.307],"ix":2},"a":{"a":0,"k":[0,0],"ix":1},"s":{"a":0,"k":[100,100],"ix":3},"r":{"a":0,"k":0,"ix":6},"o":{"a":0,"k":100,"ix":7},"sk":{"a":0,"k":0,"ix":4},"sa":{"a":0,"k":0,"ix":5},"nm":"Transform"}],"nm":"Group 1","np":4,"cix":2,"bm":0,"ix":1,"mn":"ADBE Vector Group","hd":false},{"ty":"gr","it":[{"ind":0,"ty":"sh","ix":1,"ks":{"a":0,"k":{"i":[[5.074,0.141],[-1.318,9.324],[-5.075,-0.141],[1.319,-9.324]],"o":[[-5.075,-0.141],[1.319,-9.323],[5.075,0.14],[-1.318,9.323]],"v":[[-2.387,16.881],[-9.189,-0.255],[2.387,-16.881],[9.188,0.255]],"c":true},"ix":2},"nm":"Path 1","mn":"ADBE Vector Shape - Group","hd":false},{"ty":"fl","c":{"a":0,"k":[0.204000001795,0.081999999402,0.136999990426,1],"ix":4},"o":{"a":0,"k":100,"ix":5},"r":1,"bm":0,"nm":"Fill 1","mn":"ADBE Vector Graphic - Fill","hd":false},{"ty":"tr","p":{"a":0,"k":[71.342,65.866],"ix":2},"a":{"a":0,"k":[0,0],"ix":1},"s":{"a":0,"k":[100,100],"ix":3},"r":{"a":0,"k":0,"ix":6},"o":{"a":0,"k":100,"ix":7},"sk":{"a":0,"k":0,"ix":4},"sa":{"a":0,"k":0,"ix":5},"nm":"Transform"}],"nm":"Group 2","np":4,"cix":2,"bm":0,"ix":2,"mn":"ADBE Vector Group","hd":false},{"ty":"gr","it":[{"ind":0,"ty":"sh","ix":1,"ks":{"a":0,"k":{"i":[[5.074,0.141],[-1.318,9.323],[-5.075,-0.14],[1.319,-9.323]],"o":[[-5.075,-0.14],[1.32,-9.323],[5.075,0.14],[-1.318,9.323]],"v":[[-2.387,16.88],[-9.189,-0.254],[2.387,-16.882],[9.188,0.254]],"c":true},"ix":2},"nm":"Path 1","mn":"ADBE Vector Shape - Group","hd":false},{"ty":"fl","c":{"a":0,"k":[0.204000001795,0.081999999402,0.136999990426,1],"ix":4},"o":{"a":0,"k":100,"ix":5},"r":1,"bm":0,"nm":"Fill 1","mn":"ADBE Vector Graphic - Fill","hd":false},{"ty":"tr","p":{"a":0,"k":[127.844,77.017],"ix":2},"a":{"a":0,"k":[0,0],"ix":1},"s":{"a":0,"k":[100,100],"ix":3},"r":{"a":0,"k":0,"ix":6},"o":{"a":0,"k":100,"ix":7},"sk":{"a":0,"k":0,"ix":4},"sa":{"a":0,"k":0,"ix":5},"nm":"Transform"}],"nm":"Group 3","np":4,"cix":2,"bm":0,"ix":3,"mn":"ADBE Vector Group","hd":false},{"ty":"gr","it":[{"ind":0,"ty":"sh","ix":1,"ks":{"a":0,"k":{"i":[[5.075,0.141],[-1.318,9.324],[-5.074,-0.141],[1.319,-9.324]],"o":[[-5.074,-0.141],[1.319,-9.323],[5.076,0.14],[-1.318,9.323]],"v":[[-2.388,16.881],[-9.189,-0.255],[2.386,-16.881],[9.188,0.255]],"c":true},"ix":2},"nm":"Path 1","mn":"ADBE Vector Shape - Group","hd":false},{"ty":"fl","c":{"a":0,"k":[0.204000001795,0.081999999402,0.136999990426,1],"ix":4},"o":{"a":0,"k":100,"ix":5},"r":1,"bm":0,"nm":"Fill 1","mn":"ADBE Vector Graphic - Fill","hd":false},{"ty":"tr","p":{"a":0,"k":[101.153,53.167],"ix":2},"a":{"a":0,"k":[0,0],"ix":1},"s":{"a":0,"k":[100,100],"ix":3},"r":{"a":0,"k":0,"ix":6},"o":{"a":0,"k":100,"ix":7},"sk":{"a":0,"k":0,"ix":4},"sa":{"a":0,"k":0,"ix":5},"nm":"Transform"}],"nm":"Group 4","np":4,"cix":2,"bm":0,"ix":4,"mn":"ADBE Vector Group","hd":false},{"ty":"gr","it":[{"ind":0,"ty":"sh","ix":1,"ks":{"a":0,"k":{"i":[[0,0],[17.246,-12.407],[-30.536,-8.167],[-6.767,1.302],[-10.225,24.694],[2.697,14.953],[0,0],[30.599,0.151],[33.304,-6.5],[30.031,-31.173],[-0.873,-28.632],[0,0]],"o":[[0,0],[-17.246,12.406],[7.635,2.042],[20.302,-3.909],[13.633,-32.925],[-0.899,-4.985],[0,0],[0,0],[0,0],[0,0],[0.872,28.631],[0,0]],"v":[[-43.681,-1.187],[-71.688,75.427],[-45.479,158.038],[-23.846,159.018],[22.795,112.621],[52.816,-10.543],[51.145,-17.491],[58.335,-102.207],[31.322,-128.146],[-11.369,-129.147],[-46.456,-100.239],[-45.528,-61.754]],"c":true},"ix":2},"nm":"Path 1","mn":"ADBE Vector Shape - Group","hd":false},{"ty":"fl","c":{"a":0,"k":[0.910000011968,0.616000007181,0.375999989229,1],"ix":4},"o":{"a":0,"k":100,"ix":5},"r":1,"bm":0,"nm":"Fill 1","mn":"ADBE Vector Graphic - Fill","hd":false},{"ty":"tr","p":{"a":0,"k":[89.184,160.57],"ix":2},"a":{"a":0,"k":[0,0],"ix":1},"s":{"a":0,"k":[100,100],"ix":3},"r":{"a":0,"k":0,"ix":6},"o":{"a":0,"k":100,"ix":7},"sk":{"a":0,"k":0,"ix":4},"sa":{"a":0,"k":0,"ix":5},"nm":"Transform"}],"nm":"Group 5","np":4,"cix":2,"bm":0,"ix":5,"mn":"ADBE Vector Group","hd":false}],"ip":0,"op":150.000006109625,"st":0,"bm":0},{"ddd":0,"ind":2,"ty":0,"nm":"Luoi","parent":5,"refId":"comp_0","sr":1,"ks":{"o":{"a":0,"k":100,"ix":11},"r":{"a":0,"k":0,"ix":10},"p":{"a":0,"k":[418.874,476.254,0],"ix":2},"a":{"a":0,"k":[540,540,0],"ix":1},"s":{"a":0,"k":[100,100,100],"ix":6}},"ao":0,"hasMask":true,"masksProperties":[{"inv":false,"mode":"a","pt":{"a":0,"k":{"i":[[-0.375,-15.75],[7.375,-6.25],[0,0],[7.875,-4.375],[0,0],[0,0],[0,0]],"o":[[0.375,15.75],[-11.875,7.5],[0,0],[-7.875,4.375],[0,0],[0,0],[0,0]],"v":[[605.375,418],[583.75,453.375],[540.875,461.25],[504.625,485],[486.875,485.625],[438,634],[728,560]],"c":true},"ix":1},"o":{"a":0,"k":100,"ix":3},"x":{"a":0,"k":0,"ix":4},"nm":"Mask 1"}],"sy":[{"c":{"a":0,"k":[0,0,0,1],"ix":2},"o":{"a":0,"k":75,"ix":3},"a":{"a":0,"k":120,"ix":5},"s":{"a":0,"k":5,"ix":8},"d":{"a":0,"k":5,"ix":6},"ch":{"a":0,"k":0,"ix":7},"bm":{"a":0,"k":5,"ix":1},"no":{"a":0,"k":0,"ix":9},"lc":{"a":0,"k":1,"ix":10},"ty":1,"nm":"Drop Shadow"},{"c":{"a":0,"k":[0,0,0,1],"ix":2},"o":{"a":0,"k":75,"ix":3},"a":{"a":0,"k":120,"ix":5},"s":{"a":0,"k":5,"ix":8},"d":{"a":0,"k":5,"ix":6},"ch":{"a":0,"k":0,"ix":7},"bm":{"a":0,"k":5,"ix":1},"no":{"a":0,"k":0,"ix":9},"ty":2,"nm":"Inner Shadow"},{"c":{"a":0,"k":[1,1,0.745098039216,1],"ix":5},"o":{"a":0,"k":75,"ix":2},"s":{"a":0,"k":5,"ix":10},"r":{"a":0,"k":50,"ix":11},"ch":{"a":0,"k":0,"ix":9},"bm":{"a":0,"k":11,"ix":1},"no":{"a":0,"k":0,"ix":3},"j":{"a":0,"k":0,"ix":12},"ty":3,"nm":"Outer Glow"},{"c":{"a":0,"k":[1,1,0.745098039216,1],"ix":5},"o":{"a":0,"k":75,"ix":2},"s":{"a":0,"k":5,"ix":11},"r":{"a":0,"k":50,"ix":12},"sr":{"a":0,"k":1,"ix":9},"ch":{"a":0,"k":0,"ix":10},"bm":{"a":0,"k":11,"ix":1},"no":{"a":0,"k":0,"ix":3},"j":{"a":0,"k":0,"ix":13},"ty":4,"nm":"Inner Glow"},{"c":{"a":0,"k":[1,0,0,1],"ix":2},"s":{"a":0,"k":3,"ix":3},"ty":0,"nm":"Stroke"}],"w":1080,"h":1080,"ip":0,"op":150.000006109625,"st":0,"bm":0},{"ddd":0,"ind":3,"ty":4,"nm":"mat trai Outlines","parent":5,"sr":1,"ks":{"o":{"a":0,"k":100,"ix":11},"r":{"a":0,"k":0,"ix":10},"p":{"a":0,"k":[293.569,295.188,0],"ix":2},"a":{"a":0,"k":[5.295,5.294,0],"ix":1},"s":{"a":0,"k":[100,100,100],"ix":6}},"ao":0,"sy":[{"c":{"a":0,"k":[0,0,0,1],"ix":2},"o":{"a":0,"k":75,"ix":3},"a":{"a":0,"k":120,"ix":5},"s":{"a":0,"k":5,"ix":8},"d":{"a":0,"k":5,"ix":6},"ch":{"a":0,"k":0,"ix":7},"bm":{"a":0,"k":5,"ix":1},"no":{"a":0,"k":0,"ix":9},"lc":{"a":0,"k":1,"ix":10},"ty":1,"nm":"Drop Shadow"},{"c":{"a":0,"k":[0,0,0,1],"ix":2},"o":{"a":0,"k":75,"ix":3},"a":{"a":0,"k":120,"ix":5},"s":{"a":0,"k":5,"ix":8},"d":{"a":0,"k":5,"ix":6},"ch":{"a":0,"k":0,"ix":7},"bm":{"a":0,"k":5,"ix":1},"no":{"a":0,"k":0,"ix":9},"ty":2,"nm":"Inner Shadow"},{"c":{"a":0,"k":[1,1,0.745098039216,1],"ix":5},"o":{"a":0,"k":75,"ix":2},"s":{"a":0,"k":5,"ix":10},"r":{"a":0,"k":50,"ix":11},"ch":{"a":0,"k":0,"ix":9},"bm":{"a":0,"k":11,"ix":1},"no":{"a":0,"k":0,"ix":3},"j":{"a":0,"k":0,"ix":12},"ty":3,"nm":"Outer Glow"},{"c":{"a":0,"k":[1,1,0.745098039216,1],"ix":5},"o":{"a":0,"k":75,"ix":2},"s":{"a":0,"k":5,"ix":11},"r":{"a":0,"k":50,"ix":12},"sr":{"a":0,"k":1,"ix":9},"ch":{"a":0,"k":0,"ix":10},"bm":{"a":0,"k":11,"ix":1},"no":{"a":0,"k":0,"ix":3},"j":{"a":0,"k":0,"ix":13},"ty":4,"nm":"Inner Glow"},{"c":{"a":0,"k":[1,0,0,1],"ix":2},"s":{"a":0,"k":3,"ix":3},"ty":0,"nm":"Stroke"}],"shapes":[{"ty":"gr","it":[{"ind":0,"ty":"sh","ix":1,"ks":{"a":0,"k":{"i":[[-0.611,-2.448],[-2.449,0.61],[0.611,2.449],[2.448,-0.61]],"o":[[0.611,2.449],[2.448,-0.611],[-0.611,-2.449],[-2.449,0.611]],"v":[[-4.433,1.106],[1.106,4.434],[4.433,-1.106],[-1.106,-4.434]],"c":true},"ix":2},"nm":"Path 1","mn":"ADBE Vector Shape - Group","hd":false},{"ty":"fl","c":{"a":0,"k":[1,1,1,1],"ix":4},"o":{"a":0,"k":100,"ix":5},"r":1,"bm":0,"nm":"Fill 1","mn":"ADBE Vector Graphic - Fill","hd":false},{"ty":"tr","p":{"a":0,"k":[5.294,5.294],"ix":2},"a":{"a":0,"k":[0,0],"ix":1},"s":{"a":0,"k":[100,100],"ix":3},"r":{"a":0,"k":0,"ix":6},"o":{"a":0,"k":100,"ix":7},"sk":{"a":0,"k":0,"ix":4},"sa":{"a":0,"k":0,"ix":5},"nm":"Transform"}],"nm":"Group 1","np":4,"cix":2,"bm":0,"ix":1,"mn":"ADBE Vector Group","hd":false}],"ip":0,"op":150.000006109625,"st":0,"bm":0},{"ddd":0,"ind":4,"ty":4,"nm":"mat phai Outlines","parent":5,"sr":1,"ks":{"o":{"a":0,"k":100,"ix":11},"r":{"a":0,"k":0,"ix":10},"p":{"a":0,"k":[460.812,232.791,0],"ix":2},"a":{"a":0,"k":[5.465,5.465,0],"ix":1},"s":{"a":0,"k":[100,100,100],"ix":6}},"ao":0,"sy":[{"c":{"a":0,"k":[0,0,0,1],"ix":2},"o":{"a":0,"k":75,"ix":3},"a":{"a":0,"k":120,"ix":5},"s":{"a":0,"k":5,"ix":8},"d":{"a":0,"k":5,"ix":6},"ch":{"a":0,"k":0,"ix":7},"bm":{"a":0,"k":5,"ix":1},"no":{"a":0,"k":0,"ix":9},"lc":{"a":0,"k":1,"ix":10},"ty":1,"nm":"Drop Shadow"},{"c":{"a":0,"k":[0,0,0,1],"ix":2},"o":{"a":0,"k":75,"ix":3},"a":{"a":0,"k":120,"ix":5},"s":{"a":0,"k":5,"ix":8},"d":{"a":0,"k":5,"ix":6},"ch":{"a":0,"k":0,"ix":7},"bm":{"a":0,"k":5,"ix":1},"no":{"a":0,"k":0,"ix":9},"ty":2,"nm":"Inner Shadow"},{"c":{"a":0,"k":[1,1,0.745098039216,1],"ix":5},"o":{"a":0,"k":75,"ix":2},"s":{"a":0,"k":5,"ix":10},"r":{"a":0,"k":50,"ix":11},"ch":{"a":0,"k":0,"ix":9},"bm":{"a":0,"k":11,"ix":1},"no":{"a":0,"k":0,"ix":3},"j":{"a":0,"k":0,"ix":12},"ty":3,"nm":"Outer Glow"},{"c":{"a":0,"k":[1,1,0.745098039216,1],"ix":5},"o":{"a":0,"k":75,"ix":2},"s":{"a":0,"k":5,"ix":11},"r":{"a":0,"k":50,"ix":12},"sr":{"a":0,"k":1,"ix":9},"ch":{"a":0,"k":0,"ix":10},"bm":{"a":0,"k":11,"ix":1},"no":{"a":0,"k":0,"ix":3},"j":{"a":0,"k":0,"ix":13},"ty":4,"nm":"Inner Glow"},{"c":{"a":0,"k":[1,0,0,1],"ix":2},"s":{"a":0,"k":3,"ix":3},"ty":0,"nm":"Stroke"}],"shapes":[{"ty":"gr","it":[{"ind":0,"ty":"sh","ix":1,"ks":{"a":0,"k":{"i":[[-1.126,-2.259],[2.258,-1.126],[1.127,2.258],[-2.259,1.126]],"o":[[1.126,2.258],[-2.259,1.126],[-1.126,-2.258],[2.258,-1.127]],"v":[[4.09,-2.039],[2.039,4.09],[-4.089,2.039],[-2.039,-4.089]],"c":true},"ix":2},"nm":"Path 1","mn":"ADBE Vector Shape - Group","hd":false},{"ty":"fl","c":{"a":0,"k":[1,1,1,1],"ix":4},"o":{"a":0,"k":100,"ix":5},"r":1,"bm":0,"nm":"Fill 1","mn":"ADBE Vector Graphic - Fill","hd":false},{"ty":"tr","p":{"a":0,"k":[5.465,5.466],"ix":2},"a":{"a":0,"k":[0,0],"ix":1},"s":{"a":0,"k":[100,100],"ix":3},"r":{"a":0,"k":0,"ix":6},"o":{"a":0,"k":100,"ix":7},"sk":{"a":0,"k":0,"ix":4},"sa":{"a":0,"k":0,"ix":5},"nm":"Transform"}],"nm":"Group 1","np":4,"cix":2,"bm":0,"ix":1,"mn":"ADBE Vector Group","hd":false}],"ip":0,"op":150.000006109625,"st":0,"bm":0},{"ddd":0,"ind":5,"ty":4,"nm":"dau Outlines","parent":6,"sr":1,"ks":{"o":{"a":0,"k":100,"ix":11},"r":{"a":1,"k":[{"i":{"x":[0.833],"y":[0.833]},"o":{"x":[0.167],"y":[0.167]},"t":17,"s":[0]},{"i":{"x":[0.833],"y":[0.833]},"o":{"x":[0.167],"y":[0.167]},"t":25,"s":[7]},{"i":{"x":[0.833],"y":[0.833]},"o":{"x":[0.167],"y":[0.167]},"t":58,"s":[7]},{"i":{"x":[0.833],"y":[0.833]},"o":{"x":[0.167],"y":[0.167]},"t":65,"s":[0]},{"i":{"x":[0.833],"y":[0.833]},"o":{"x":[0.167],"y":[0.167]},"t":98,"s":[0]},{"i":{"x":[0.833],"y":[0.833]},"o":{"x":[0.167],"y":[0.167]},"t":106,"s":[7]},{"i":{"x":[0.833],"y":[0.833]},"o":{"x":[0.167],"y":[0.167]},"t":136,"s":[7]},{"t":143.000005824509,"s":[0]}],"ix":10},"p":{"a":0,"k":[341.696,100.397,0],"ix":2},"a":{"a":0,"k":[427.972,426.482,0],"ix":1},"s":{"a":0,"k":[100,100,100],"ix":6}},"ao":0,"sy":[{"c":{"a":0,"k":[0,0,0,1],"ix":2},"o":{"a":0,"k":75,"ix":3},"a":{"a":0,"k":120,"ix":5},"s":{"a":0,"k":5,"ix":8},"d":{"a":0,"k":5,"ix":6},"ch":{"a":0,"k":0,"ix":7},"bm":{"a":0,"k":5,"ix":1},"no":{"a":0,"k":0,"ix":9},"lc":{"a":0,"k":1,"ix":10},"ty":1,"nm":"Drop Shadow"},{"c":{"a":0,"k":[0,0,0,1],"ix":2},"o":{"a":0,"k":75,"ix":3},"a":{"a":0,"k":120,"ix":5},"s":{"a":0,"k":5,"ix":8},"d":{"a":0,"k":5,"ix":6},"ch":{"a":0,"k":0,"ix":7},"bm":{"a":0,"k":5,"ix":1},"no":{"a":0,"k":0,"ix":9},"ty":2,"nm":"Inner Shadow"},{"c":{"a":0,"k":[1,1,0.745098039216,1],"ix":5},"o":{"a":0,"k":75,"ix":2},"s":{"a":0,"k":5,"ix":10},"r":{"a":0,"k":50,"ix":11},"ch":{"a":0,"k":0,"ix":9},"bm":{"a":0,"k":11,"ix":1},"no":{"a":0,"k":0,"ix":3},"j":{"a":0,"k":0,"ix":12},"ty":3,"nm":"Outer Glow"},{"c":{"a":0,"k":[1,1,0.745098039216,1],"ix":5},"o":{"a":0,"k":75,"ix":2},"s":{"a":0,"k":5,"ix":11},"r":{"a":0,"k":50,"ix":12},"sr":{"a":0,"k":1,"ix":9},"ch":{"a":0,"k":0,"ix":10},"bm":{"a":0,"k":11,"ix":1},"no":{"a":0,"k":0,"ix":3},"j":{"a":0,"k":0,"ix":13},"ty":4,"nm":"Inner Glow"},{"c":{"a":0,"k":[1,0,0,1],"ix":2},"s":{"a":0,"k":3,"ix":3},"ty":0,"nm":"Stroke"}],"shapes":[{"ty":"gr","it":[{"ind":0,"ty":"sh","ix":1,"ks":{"a":0,"k":{"i":[[1.567,1.669],[1.639,-1.537],[0,0],[0.062,-1.031],[0.397,-7.479],[0.089,-4.727],[0.828,-1.804],[2.652,-2.898],[3.04,-2.889],[0,0],[0.231,-0.167],[1.611,-0.612],[4.026,-0.743],[5.046,-0.412],[1.504,-0.083],[0.402,-0.018],[0.102,-0.004],[0,0],[0.613,-0.402],[0,0],[2.016,-0.159],[4.194,2.11],[4.792,4.556],[1.516,1.577],[0.523,0.524],[0.26,0.233],[0.195,0.148],[0.156,0.099],[0.327,0.14],[0.29,0.081],[0.633,0.121],[2.708,0.365],[0.011,0.001],[0.232,-2.253],[-2.256,-0.275],[-0.351,-0.043],[-2.955,-0.427],[-1.11,-0.197],[-0.308,-0.065],[-0.091,-0.093],[-3.469,-3.3],[-7.804,-3.836],[-4.306,-0.303],[-4.014,2.511],[0,0],[0,0],[-7.601,0.936],[-4.695,1.148],[-2.04,0.779],[-1.622,1.168],[-0.433,0.411],[0,0],[-3.593,4.523],[-1.191,2.583],[-0.055,2.974],[-0.397,7.44],[-0.143,2.508],[-0.039,0.657],[0,0]],"o":[[-1.567,-1.669],[0,0],[-0.747,0.701],[0,0.005],[-0.399,7.488],[-0.03,1.624],[-1.234,2.702],[-2.647,2.905],[0,0],[-0.146,0.14],[-0.78,0.57],[-2.823,1.084],[-6.048,1.122],[-2.524,0.206],[-0.752,0.041],[-0.201,0.009],[0,0],[-0.738,0.027],[0,0],[-1.864,1.149],[-3.512,0.282],[-6.289,-3.136],[-2.403,-2.278],[-0.762,-0.79],[-0.265,-0.265],[-0.132,-0.118],[-0.099,-0.075],[-0.159,-0.098],[-0.41,-0.169],[-0.527,-0.14],[-2.185,-0.413],[-2.698,-0.364],[-2.256,-0.275],[-0.232,2.252],[0,0],[1.229,0.154],[1.476,0.214],[0.459,0.081],[0.078,0.079],[1.389,1.416],[5.231,4.963],[3.909,1.91],[4.29,0.311],[0,0],[0,0],[2.603,-0.125],[4.845,-0.598],[2.349,-0.575],[2.04,-0.785],[0.484,-0.351],[0,0],[4.007,-3.816],[1.795,-2.267],[1.186,-2.579],[0.082,-4.47],[0.198,-3.725],[0.057,-0.984],[0,0],[1.64,-1.537]],"v":[[87.332,-53.38],[81.526,-53.619],[73.757,-46.334],[72.495,-43.632],[71.722,-29.828],[70.815,-9.011],[69.531,-3.899],[63.481,4.601],[54.685,13.303],[54.687,13.299],[54.121,13.764],[50.446,15.614],[39.804,18.384],[22.118,20.619],[15.949,21.043],[14.203,21.131],[13.747,21.15],[13.601,21.156],[11.529,21.814],[-23.441,44.771],[-29.185,46.643],[-40.978,43.709],[-58.391,30.747],[-64.338,24.8],[-66.251,22.828],[-67.009,22.101],[-67.473,21.716],[-67.841,21.46],[-68.52,21.105],[-69.489,20.783],[-71.193,20.409],[-79.271,19.177],[-84.161,18.545],[-88.667,22.125],[-85.003,26.702],[-84.458,26.769],[-77.157,27.746],[-73.133,28.38],[-71.985,28.601],[-71.731,28.859],[-64.172,36.48],[-44.145,51.241],[-31.784,54.845],[-18.999,51.767],[-18.916,51.714],[15.2,29.318],[32.175,27.871],[46.886,25.308],[53.506,23.297],[59.019,20.452],[60.396,19.314],[60.4,19.311],[72.427,6.89],[77.004,-0.348],[79.027,-8.703],[79.923,-29.237],[80.457,-38.909],[80.6,-41.382],[87.202,-47.574]],"c":true},"ix":2},"nm":"Path 1","mn":"ADBE Vector Shape - Group","hd":false},{"ty":"fl","c":{"a":0,"k":[0.204000001795,0.081999999402,0.136999990426,1],"ix":4},"o":{"a":0,"k":100,"ix":5},"r":1,"bm":0,"nm":"Fill 1","mn":"ADBE Vector Graphic - Fill","hd":false},{"ty":"tr","p":{"a":0,"k":[404.984,368.282],"ix":2},"a":{"a":0,"k":[0,0],"ix":1},"s":{"a":0,"k":[100,100],"ix":3},"r":{"a":0,"k":0,"ix":6},"o":{"a":0,"k":100,"ix":7},"sk":{"a":0,"k":0,"ix":4},"sa":{"a":0,"k":0,"ix":5},"nm":"Transform"}],"nm":"Group 1","np":4,"cix":2,"bm":0,"ix":1,"mn":"ADBE Vector Group","hd":false},{"ty":"gr","it":[{"ind":0,"ty":"sh","ix":1,"ks":{"a":0,"k":{"i":[[0,0],[0.462,-9.132],[1.611,-5.49],[0.607,-1.105],[0,0],[14.261,5.184],[0.501,0.286],[0.203,0.094],[1.33,1.023],[0,0],[-0.237,0.102],[0,0],[0,0],[0,0],[0,0]],"o":[[0,0],[-0.461,9.133],[-0.295,1.348],[-1.988,3.796],[-36.644,38.148],[-1.014,-0.044],[-0.205,-0.057],[-0.999,-0.412],[-1.841,-1.01],[0,0],[-7.35,-6.334],[0,0],[0,0],[0,0],[0,0]],"v":[[59.717,-45.029],[55.809,-28.075],[52.856,-2.946],[51.475,0.744],[46.384,6.881],[-34.116,36.633],[-36.444,36.159],[-37.038,35.932],[-40.558,33.693],[-43.386,31.937],[-42.965,31.754],[-59.717,14.708],[-41.931,13.219],[-5.655,-12.318],[39.515,-17.467]],"c":true},"ix":2},"nm":"Path 1","mn":"ADBE Vector Shape - Group","hd":false},{"ty":"fl","c":{"a":0,"k":[0.823999980852,0.481999984442,0.416000007181,1],"ix":4},"o":{"a":0,"k":100,"ix":5},"r":1,"bm":0,"nm":"Fill 1","mn":"ADBE Vector Graphic - Fill","hd":false},{"ty":"tr","p":{"a":0,"k":[422.409,403.745],"ix":2},"a":{"a":0,"k":[0,0],"ix":1},"s":{"a":0,"k":[100,100],"ix":3},"r":{"a":0,"k":0,"ix":6},"o":{"a":0,"k":100,"ix":7},"sk":{"a":0,"k":0,"ix":4},"sa":{"a":0,"k":0,"ix":5},"nm":"Transform"}],"nm":"Group 2","np":4,"cix":2,"bm":0,"ix":2,"mn":"ADBE Vector Group","hd":false},{"ty":"gr","it":[{"ind":0,"ty":"sh","ix":1,"ks":{"a":0,"k":{"i":[[1.628,0.79],[8.088,7.22],[1.205,-1.35],[-1.35,-1.205],[-10.307,-5.004],[-0.79,1.628]],"o":[[-9.861,-4.785],[-1.35,-1.205],[-1.205,1.351],[8.647,7.715],[1.628,0.791],[0.791,-1.628]],"v":[[15.516,6.28],[-11.992,-11.762],[-16.619,-11.499],[-16.356,-6.872],[12.654,12.176],[17.033,10.659]],"c":true},"ix":2},"nm":"Path 1","mn":"ADBE Vector Shape - Group","hd":false},{"ty":"fl","c":{"a":0,"k":[0.8,0.513999968884,0.322000002394,1],"ix":4},"o":{"a":0,"k":100,"ix":5},"r":1,"bm":0,"nm":"Fill 1","mn":"ADBE Vector Graphic - Fill","hd":false},{"ty":"tr","p":{"a":0,"k":[335.286,172.33],"ix":2},"a":{"a":0,"k":[0,0],"ix":1},"s":{"a":0,"k":[100,100],"ix":3},"r":{"a":0,"k":0,"ix":6},"o":{"a":0,"k":100,"ix":7},"sk":{"a":0,"k":0,"ix":4},"sa":{"a":0,"k":0,"ix":5},"nm":"Transform"}],"nm":"Group 3","np":4,"cix":2,"bm":0,"ix":3,"mn":"ADBE Vector Group","hd":false},{"ty":"gr","it":[{"ind":0,"ty":"sh","ix":1,"ks":{"a":0,"k":{"i":[[1.634,0.779],[0,0],[8.017,5.285],[3.813,3.4],[2.211,3.667],[0.488,1.849],[1.75,-0.462],[-0.462,-1.75],[-1.419,-2.348],[-4.212,-3.735],[-5.6,-3.307],[-0.063,-0.031],[-0.778,1.634]],"o":[[0,0],[-0.342,-0.163],[-4.007,-2.64],[-3.814,-3.395],[-1.162,-1.921],[-0.462,-1.749],[-1.75,0.463],[0.683,2.582],[2.756,4.549],[6.319,5.594],[5.598,3.303],[1.634,0.779],[0.78,-1.633]],"v":[[21.89,15.254],[21.877,15.248],[6.542,6.427],[-5.544,-2.73],[-14.92,-13.478],[-17.42,-19.156],[-21.425,-21.487],[-23.756,-17.481],[-20.529,-10.087],[-9.707,2.338],[9.364,15.907],[19.069,21.17],[23.437,19.622]],"c":true},"ix":2},"nm":"Path 1","mn":"ADBE Vector Shape - Group","hd":false},{"ty":"fl","c":{"a":0,"k":[0.8,0.513999968884,0.322000002394,1],"ix":4},"o":{"a":0,"k":100,"ix":5},"r":1,"bm":0,"nm":"Fill 1","mn":"ADBE Vector Graphic - Fill","hd":false},{"ty":"tr","p":{"a":0,"k":[293.868,180.431],"ix":2},"a":{"a":0,"k":[0,0],"ix":1},"s":{"a":0,"k":[100,100],"ix":3},"r":{"a":0,"k":0,"ix":6},"o":{"a":0,"k":100,"ix":7},"sk":{"a":0,"k":0,"ix":4},"sa":{"a":0,"k":0,"ix":5},"nm":"Transform"}],"nm":"Group 4","np":4,"cix":2,"bm":0,"ix":4,"mn":"ADBE Vector Group","hd":false},{"ty":"gr","it":[{"ind":0,"ty":"sh","ix":1,"ks":{"a":0,"k":{"i":[[0.536,16.05],[3.364,5.633],[0,0],[-50.905,-10.523],[-32.361,-25.537],[9.966,-61.9],[14.321,-7.333],[27.575,-17.285],[43.284,4.031],[29.104,7.876],[0,0.008],[0.465,0.364],[2.673,14.317],[0,0]],"o":[[-38.988,-31.331],[-8.651,-14.486],[0,0],[0,0],[0,0],[0,0],[0,0],[0,0],[0,0],[-44.225,21.996],[-0.461,-0.361],[-31.446,12.432],[-0.717,1.655],[-36.072,10.76]],"v":[[-75.424,8.057],[-150.705,-56.262],[-147.493,-105.029],[-54.49,-127.821],[33.431,-111.443],[135.052,3.359],[131.37,26.661],[131.78,69.924],[104.074,97.515],[62.085,116.348],[12.929,78.021],[11.539,76.932],[-32.178,43.135],[-33.398,45.791]],"c":true},"ix":2},"nm":"Path 1","mn":"ADBE Vector Shape - Group","hd":false},{"ty":"fl","c":{"a":0,"k":[0.8,0.513999968884,0.322000002394,1],"ix":4},"o":{"a":0,"k":100,"ix":5},"r":1,"bm":0,"nm":"Fill 1","mn":"ADBE Vector Graphic - Fill","hd":false},{"ty":"tr","p":{"a":0,"k":[588.339,156.88],"ix":2},"a":{"a":0,"k":[0,0],"ix":1},"s":{"a":0,"k":[100,100],"ix":3},"r":{"a":0,"k":0,"ix":6},"o":{"a":0,"k":100,"ix":7},"sk":{"a":0,"k":0,"ix":4},"sa":{"a":0,"k":0,"ix":5},"nm":"Transform"}],"nm":"Group 5","np":4,"cix":2,"bm":0,"ix":5,"mn":"ADBE Vector Group","hd":false},{"ty":"gr","it":[{"ind":0,"ty":"sh","ix":1,"ks":{"a":0,"k":{"i":[[11.138,11.57],[1.696,6.338],[0,0],[27.927,-43.842],[4.235,-41.005],[-51.34,-35.989],[-15.239,5.162],[-31.613,7.733],[-27.272,33.853],[-14.634,26.363],[0.006,0.006],[-0.063,0.588],[8.405,11.894],[0,0]],"o":[[4.699,-49.796],[-4.361,-16.299],[0,0],[0,0],[0,0],[0,0],[0,0],[0,0],[0,0],[46.594,-16.389],[0.063,-0.582],[30.83,-13.889],[1.686,0.64],[32.855,-18.373]],"v":[[85.376,-47.217],[91.706,-146.031],[54.492,-177.712],[-26.665,-126.893],[-76.186,-52.421],[-64.667,100.463],[-45.389,114.06],[-14.648,144.502],[24.449,143.859],[67.217,126.868],[73.983,64.904],[74.172,63.149],[80.397,8.243],[83.151,9.22]],"c":true},"ix":2},"nm":"Path 1","mn":"ADBE Vector Shape - Group","hd":false},{"ty":"fl","c":{"a":0,"k":[0.8,0.513999968884,0.322000002394,1],"ix":4},"o":{"a":0,"k":100,"ix":5},"r":1,"bm":0,"nm":"Fill 1","mn":"ADBE Vector Graphic - Fill","hd":false},{"ty":"tr","p":{"a":0,"k":[116.256,357.633],"ix":2},"a":{"a":0,"k":[0,0],"ix":1},"s":{"a":0,"k":[100,100],"ix":3},"r":{"a":0,"k":0,"ix":6},"o":{"a":0,"k":100,"ix":7},"sk":{"a":0,"k":0,"ix":4},"sa":{"a":0,"k":0,"ix":5},"nm":"Transform"}],"nm":"Group 6","np":4,"cix":2,"bm":0,"ix":6,"mn":"ADBE Vector Group","hd":false},{"ty":"gr","it":[{"ind":0,"ty":"sh","ix":1,"ks":{"a":0,"k":{"i":[[-0.459,2.141],[0.836,-0.091],[2.162,5.054],[0.953,2.321],[0.322,0.83],[0.084,0.277],[1.691,-0.523],[-0.523,-1.692],[-0.422,-1.08],[-2.416,-5.589],[-0.012,-0.028],[-1.014,-0.722],[-1.283,0.189]],"o":[[-0.811,0.15],[-1.221,-2.79],[-1.234,-2.884],[-0.476,-1.16],[-0.32,-0.822],[-0.523,-1.691],[-1.692,0.522],[0.206,0.663],[1.468,3.736],[2.408,5.568],[1.119,0.538],[1.349,-0.06],[-0.29,-2.202]],"v":[[10.001,10.589],[7.532,10.958],[1.887,-2.07],[-1.502,-10.12],[-2.715,-13.139],[-3.353,-14.889],[-7.362,-17.005],[-9.478,-12.997],[-8.539,-10.428],[-1.889,5.375],[2.578,15.624],[5.776,17.529],[9.721,17.143]],"c":true},"ix":2},"nm":"Path 1","mn":"ADBE Vector Shape - Group","hd":false},{"ty":"fl","c":{"a":0,"k":[0.204000001795,0.081999999402,0.136999990426,1],"ix":4},"o":{"a":0,"k":100,"ix":5},"r":1,"bm":0,"nm":"Fill 1","mn":"ADBE Vector Graphic - Fill","hd":false},{"ty":"tr","p":{"a":0,"k":[415.943,383.036],"ix":2},"a":{"a":0,"k":[0,0],"ix":1},"s":{"a":0,"k":[100,100],"ix":3},"r":{"a":0,"k":0,"ix":6},"o":{"a":0,"k":100,"ix":7},"sk":{"a":0,"k":0,"ix":4},"sa":{"a":0,"k":0,"ix":5},"nm":"Transform"}],"nm":"Group 7","np":4,"cix":2,"bm":0,"ix":7,"mn":"ADBE Vector Group","hd":false},{"ty":"gr","it":[{"ind":0,"ty":"sh","ix":1,"ks":{"a":0,"k":{"i":[[-0.443,-0.983],[-2.302,-5.597],[-0.764,-1.879],[-0.12,-0.294],[0.452,-0.331],[-1.883,-1.411],[-0.379,0.358],[0.492,1.22],[2.743,6.633],[1.221,2.843],[0.474,1.049],[0.331,0.61],[1.554,-0.847],[-0.847,-1.554]],"o":[[1.574,3.483],[1.153,2.802],[0.141,0.344],[-0.44,0.363],[2.234,0.737],[0.387,-0.336],[0.955,-0.905],[-0.002,-0.005],[-1.371,-3.317],[-0.61,-1.421],[-0.478,-1.056],[-0.846,-1.555],[-1.555,0.847],[0.161,0.292]],"v":[[-7.709,-10.42],[-1.117,5.171],[1.852,12.432],[2.239,13.382],[0.899,14.419],[7.117,17.653],[8.268,16.614],[9.036,13.086],[3.799,0.277],[-0.227,-9.314],[-1.867,-13.059],[-3.052,-15.524],[-7.399,-16.806],[-8.68,-12.458]],"c":true},"ix":2},"nm":"Path 1","mn":"ADBE Vector Shape - Group","hd":false},{"ty":"fl","c":{"a":0,"k":[0.204000001795,0.081999999402,0.136999990426,1],"ix":4},"o":{"a":0,"k":100,"ix":5},"r":1,"bm":0,"nm":"Fill 1","mn":"ADBE Vector Graphic - Fill","hd":false},{"ty":"tr","p":{"a":0,"k":[415.058,383.226],"ix":2},"a":{"a":0,"k":[0,0],"ix":1},"s":{"a":0,"k":[100,100],"ix":3},"r":{"a":0,"k":0,"ix":6},"o":{"a":0,"k":100,"ix":7},"sk":{"a":0,"k":0,"ix":4},"sa":{"a":0,"k":0,"ix":5},"nm":"Transform"}],"nm":"Group 8","np":4,"cix":2,"bm":0,"ix":8,"mn":"ADBE Vector Group","hd":false},{"ty":"gr","it":[{"ind":0,"ty":"sh","ix":1,"ks":{"a":0,"k":{"i":[[13.916,-6.939],[6.036,2.934],[1.093,4.942],[0,0],[-13.984,2.006],[-10.608,-5.684],[1.114,-14.883]],"o":[[0,0],[-6.036,-2.934],[-1.093,-4.942],[0,0],[24.893,-3.573],[10.608,5.685],[-0.879,11.749]],"v":[[14.003,33.247],[-12.335,33.627],[-34.637,9.996],[-35.911,3.772],[-22.715,-15.611],[20.735,-30.877],[35.585,1.348]],"c":true},"ix":2},"nm":"Path 1","mn":"ADBE Vector Shape - Group","hd":false},{"ty":"fl","c":{"a":0,"k":[0.204000001795,0.081999999402,0.136999990426,1],"ix":4},"o":{"a":0,"k":100,"ix":5},"r":1,"bm":0,"nm":"Fill 1","mn":"ADBE Vector Graphic - Fill","hd":false},{"ty":"tr","p":{"a":0,"k":[400.252,342.984],"ix":2},"a":{"a":0,"k":[0,0],"ix":1},"s":{"a":0,"k":[100,100],"ix":3},"r":{"a":0,"k":0,"ix":6},"o":{"a":0,"k":100,"ix":7},"sk":{"a":0,"k":0,"ix":4},"sa":{"a":0,"k":0,"ix":5},"nm":"Transform"}],"nm":"Group 9","np":4,"cix":2,"bm":0,"ix":9,"mn":"ADBE Vector Group","hd":false},{"ty":"gr","it":[{"ind":0,"ty":"sh","ix":1,"ks":{"a":0,"k":{"i":[[0,0],[0,0],[0,0],[1.084,-0.771],[8.802,-19.881],[3.677,-12.409],[-12.823,-29.564],[-24.717,-33.601],[-30.418,28.332],[-14.308,48.902],[0,0],[6.6,41.188]],"o":[[-12.067,-29.88],[-11.422,-6.087],[-20.341,-7.679],[-1.31,0.231],[0,0],[0,0],[0,0],[24.717,33.602],[0,0],[47.507,16.629],[41.531,-1.794],[-6.598,-41.188]],"v":[[82.474,-88.823],[30.485,-109.155],[-3.124,-105.719],[-40.448,-101.685],[-69.512,-77.921],[-95.541,-56.385],[-117.532,-5.075],[-120.008,70.591],[-30.678,90.371],[30.377,67.462],[89.54,40.032],[138.125,-37.496]],"c":true},"ix":2},"nm":"Path 1","mn":"ADBE Vector Shape - Group","hd":false},{"ty":"fl","c":{"a":0,"k":[1,0.736999990426,0.486000001197,1],"ix":4},"o":{"a":0,"k":100,"ix":5},"r":1,"bm":0,"nm":"Fill 1","mn":"ADBE Vector Graphic - Fill","hd":false},{"ty":"tr","p":{"a":0,"k":[412.015,370.228],"ix":2},"a":{"a":0,"k":[0,0],"ix":1},"s":{"a":0,"k":[100,100],"ix":3},"r":{"a":0,"k":0,"ix":6},"o":{"a":0,"k":100,"ix":7},"sk":{"a":0,"k":0,"ix":4},"sa":{"a":0,"k":0,"ix":5},"nm":"Transform"}],"nm":"Group 10","np":4,"cix":2,"bm":0,"ix":10,"mn":"ADBE Vector Group","hd":false},{"ty":"gr","it":[{"ind":0,"ty":"sh","ix":1,"ks":{"a":0,"k":{"i":[[-0.663,9.297],[-22.455,5.71],[0.858,-4.391],[16.838,-2.3]],"o":[[0,0],[22.454,-5.71],[-0.859,4.391],[-16.838,2.3]],"v":[[-23.136,6.803],[-3.953,-19.529],[25.55,-0.709],[7.469,22.94]],"c":true},"ix":2},"nm":"Path 1","mn":"ADBE Vector Shape - Group","hd":false},{"ty":"fl","c":{"a":0,"k":[0.204000001795,0.081999999402,0.136999990426,1],"ix":4},"o":{"a":0,"k":100,"ix":5},"r":1,"bm":0,"nm":"Fill 1","mn":"ADBE Vector Graphic - Fill","hd":false},{"ty":"tr","p":{"a":0,"k":[472.559,237.993],"ix":2},"a":{"a":0,"k":[0,0],"ix":1},"s":{"a":0,"k":[100,100],"ix":3},"r":{"a":0,"k":0,"ix":6},"o":{"a":0,"k":100,"ix":7},"sk":{"a":0,"k":0,"ix":4},"sa":{"a":0,"k":0,"ix":5},"nm":"Transform"}],"nm":"Group 11","np":4,"cix":2,"bm":0,"ix":11,"mn":"ADBE Vector Group","hd":false},{"ty":"gr","it":[{"ind":0,"ty":"sh","ix":1,"ks":{"a":0,"k":{"i":[[6.544,6.638],[20.78,-10.245],[-3.505,-2.781],[-14.296,9.19]],"o":[[0,0],[-20.781,10.246],[3.505,2.78],[14.296,-9.19]],"v":[[22.963,-11.768],[-8.726,-19.327],[-18.932,14.148],[10.177,20.382]],"c":true},"ix":2},"nm":"Path 1","mn":"ADBE Vector Shape - Group","hd":false},{"ty":"fl","c":{"a":0,"k":[0.204000001795,0.081999999402,0.136999990426,1],"ix":4},"o":{"a":0,"k":100,"ix":5},"r":1,"bm":0,"nm":"Fill 1","mn":"ADBE Vector Graphic - Fill","hd":false},{"ty":"tr","p":{"a":0,"k":[288.134,307.962],"ix":2},"a":{"a":0,"k":[0,0],"ix":1},"s":{"a":0,"k":[100,100],"ix":3},"r":{"a":0,"k":0,"ix":6},"o":{"a":0,"k":100,"ix":7},"sk":{"a":0,"k":0,"ix":4},"sa":{"a":0,"k":0,"ix":5},"nm":"Transform"}],"nm":"Group 12","np":4,"cix":2,"bm":0,"ix":12,"mn":"ADBE Vector Group","hd":false},{"ty":"gr","it":[{"ind":0,"ty":"sh","ix":1,"ks":{"a":0,"k":{"i":[[-23.841,59.423],[-23.674,20.607],[-31.815,0.9],[-61.936,-12.045],[-40.218,-39.802],[-18.585,-33.865],[-18.912,-58.35],[61.366,-42.044],[52.506,-39.386],[72.375,-5.281],[45.398,43.382],[8.514,65.237],[-29.28,87.663]],"o":[[0,0],[0,0],[0,0],[0,0],[0,0],[0,0],[0,0],[0,0],[0,0],[0,0],[0,0],[0,0],[0,0]],"v":[[-227.025,-75.341],[-214.295,-121.3],[-171.479,-168.179],[-72.801,-220.705],[36.834,-223.643],[92.899,-201.425],[157.47,-157.041],[189.499,11.018],[183.422,121.383],[101.073,187.095],[-33.884,220.063],[-123.662,167.18],[-179.263,17.036]],"c":true},"ix":2},"nm":"Path 1","mn":"ADBE Vector Shape - Group","hd":false},{"ty":"fl","c":{"a":0,"k":[0.910000011968,0.616000007181,0.375999989229,1],"ix":4},"o":{"a":0,"k":100,"ix":5},"r":1,"bm":0,"nm":"Fill 1","mn":"ADBE Vector Graphic - Fill","hd":false},{"ty":"tr","p":{"a":0,"k":[377.094,264.933],"ix":2},"a":{"a":0,"k":[0,0],"ix":1},"s":{"a":0,"k":[100,100],"ix":3},"r":{"a":0,"k":0,"ix":6},"o":{"a":0,"k":100,"ix":7},"sk":{"a":0,"k":0,"ix":4},"sa":{"a":0,"k":0,"ix":5},"nm":"Transform"}],"nm":"Group 13","np":4,"cix":2,"bm":0,"ix":13,"mn":"ADBE Vector Group","hd":false},{"ty":"gr","it":[{"ind":0,"ty":"sh","ix":1,"ks":{"a":0,"k":{"i":[[-24.274,60.502],[-24.104,20.983],[-32.394,0.917],[-63.062,-12.264],[-40.949,-40.525],[-18.922,-34.48],[-19.255,-59.41],[62.48,-42.808],[53.46,-40.101],[73.689,-5.378],[46.223,44.17],[8.669,66.424],[-29.812,89.255]],"o":[[0,0],[0,0],[0,0],[0,0],[0,0],[0,0],[0,0],[0,0],[0,0],[0,0],[0,0],[0,0],[0,0]],"v":[[-231.149,-76.71],[-218.188,-123.504],[-174.593,-171.234],[-74.124,-224.715],[37.504,-227.706],[94.587,-205.085],[160.332,-159.895],[192.944,11.219],[186.756,123.589],[102.91,190.495],[-34.499,224.061],[-125.908,170.217],[-182.52,17.346]],"c":true},"ix":2},"nm":"Path 1","mn":"ADBE Vector Shape - Group","hd":false},{"ty":"fl","c":{"a":0,"k":[0.8,0.513999968884,0.322000002394,1],"ix":4},"o":{"a":0,"k":100,"ix":5},"r":1,"bm":0,"nm":"Fill 1","mn":"ADBE Vector Graphic - Fill","hd":false},{"ty":"tr","p":{"a":0,"k":[376.592,268.482],"ix":2},"a":{"a":0,"k":[0,0],"ix":1},"s":{"a":0,"k":[100,100],"ix":3},"r":{"a":0,"k":0,"ix":6},"o":{"a":0,"k":100,"ix":7},"sk":{"a":0,"k":0,"ix":4},"sa":{"a":0,"k":0,"ix":5},"nm":"Transform"}],"nm":"Group 14","np":4,"cix":2,"bm":0,"ix":14,"mn":"ADBE Vector Group","hd":false}],"ip":0,"op":150.000006109625,"st":0,"bm":0},{"ddd":0,"ind":6,"ty":4,"nm":"than Outlines","sr":1,"ks":{"o":{"a":0,"k":100,"ix":11},"r":{"a":0,"k":0,"ix":10},"p":{"a":0,"k":[555.874,485.875,0],"ix":2},"a":{"a":0,"k":[356.971,87.795,0],"ix":1},"s":{"a":0,"k":[100,100,100],"ix":6}},"ao":0,"ef":[{"ty":34,"nm":"Puppet","np":5,"mn":"ADBE FreePin3","ix":1,"en":1,"ef":[{"ty":7,"nm":"Puppet Engine","mn":"ADBE FreePin3 Puppet Engine","ix":1,"v":{"a":0,"k":1,"ix":1}},{"ty":7,"nm":"On Transparent","mn":"ADBE FreePin3 On Transparent","ix":2,"v":{"a":0,"k":0,"ix":2}},{"ty":29.9700012207031,"nm":"arap","np":3,"mn":"ADBE FreePin3 ARAP Group","ix":3,"en":1,"ef":[{"ty":6,"nm":"Auto-traced Shapes","mn":"ADBE FreePin3 Outlines","ix":1,"v":0},{"ty":1,"nm":"Mesh","np":2,"mn":"ADBE FreePin3 Mesh Group","ix":2,"en":1,"ef":[{"nm":"Mesh 1","np":7,"mn":"ADBE FreePin3 Mesh Atom","ix":1,"en":1,"ef":[{"ty":6,"nm":"Mesh","mn":"ADBE FreePin3 Mesh","ix":1,"v":0},{"ty":0,"nm":"Triangles","mn":"ADBE FreePin3 Mesh Tri Count","ix":2,"v":{"a":0,"k":350,"ix":2}},{"ty":0,"nm":"Expansion","mn":"ADBE FreePin3 Mesh Expansion","ix":3,"v":{"a":0,"k":3,"ix":3}},{"nm":"Deform","np":6,"mn":"ADBE FreePin3 PosPins","ix":4,"en":1,"ef":[{"nm":"Puppet Pin 5","np":7,"mn":"ADBE FreePin3 PosPin Atom","ix":1,"en":1,"ef":[{"ty":3,"nm":"Vertex Offset","mn":"ADBE FreePin3 PosPin Vtx Offset","ix":1,"v":{"a":0,"k":[25.246,9.344],"ix":1}},{"ty":0,"nm":"Vertex Index","mn":"ADBE FreePin3 PosPin Vtx Index","ix":2,"v":{"a":0,"k":227,"ix":2}},{"ty":7,"nm":"Pin Type","mn":"ADBE FreePin3 PosPin Type","ix":3,"v":{"a":0,"k":1,"ix":3}},{"ty":3,"nm":"Position","mn":"ADBE FreePin3 PosPin Position","ix":4,"v":{"a":0,"k":[570,610],"ix":4}},{"ty":0,"nm":"Scale","mn":"ADBE FreePin3 PosPin Scale","ix":5,"v":{"a":0,"k":100,"ix":5}},{"ty":0,"nm":"Rotation","mn":"ADBE FreePin3 PosPin Rotation","ix":6,"v":{"a":0,"k":0,"ix":6}}]},{"nm":"Puppet Pin 4","np":7,"mn":"ADBE FreePin3 PosPin Atom","ix":2,"en":1,"ef":[{"ty":3,"nm":"Vertex Offset","mn":"ADBE FreePin3 PosPin Vtx Offset","ix":1,"v":{"a":0,"k":[-9.02,3.639],"ix":1}},{"ty":0,"nm":"Vertex Index","mn":"ADBE FreePin3 PosPin Vtx Index","ix":2,"v":{"a":0,"k":187,"ix":2}},{"ty":7,"nm":"Pin Type","mn":"ADBE FreePin3 PosPin Type","ix":3,"v":{"a":0,"k":1,"ix":3}},{"ty":3,"nm":"Position","mn":"ADBE FreePin3 PosPin Position","ix":4,"v":{"a":0,"k":[746,858],"ix":4}},{"ty":0,"nm":"Scale","mn":"ADBE FreePin3 PosPin Scale","ix":5,"v":{"a":0,"k":100,"ix":5}},{"ty":0,"nm":"Rotation","mn":"ADBE FreePin3 PosPin Rotation","ix":6,"v":{"a":0,"k":0,"ix":6}}]},{"nm":"Puppet Pin 3","np":7,"mn":"ADBE FreePin3 PosPin Atom","ix":3,"en":1,"ef":[{"ty":3,"nm":"Vertex Offset","mn":"ADBE FreePin3 PosPin Vtx Offset","ix":1,"v":{"a":0,"k":[-9.679,-5.072],"ix":1}},{"ty":0,"nm":"Vertex Index","mn":"ADBE FreePin3 PosPin Vtx Index","ix":2,"v":{"a":0,"k":181,"ix":2}},{"ty":7,"nm":"Pin Type","mn":"ADBE FreePin3 PosPin Type","ix":3,"v":{"a":0,"k":1,"ix":3}},{"ty":3,"nm":"Position","mn":"ADBE FreePin3 PosPin Position","ix":4,"v":{"a":0,"k":[463,884],"ix":4}},{"ty":0,"nm":"Scale","mn":"ADBE FreePin3 PosPin Scale","ix":5,"v":{"a":0,"k":100,"ix":5}},{"ty":0,"nm":"Rotation","mn":"ADBE FreePin3 PosPin Rotation","ix":6,"v":{"a":0,"k":0,"ix":6}}]},{"nm":"Puppet Pin 2","np":7,"mn":"ADBE FreePin3 PosPin Atom","ix":4,"en":1,"ef":[{"ty":3,"nm":"Vertex Offset","mn":"ADBE FreePin3 PosPin Vtx Offset","ix":1,"v":{"a":0,"k":[24.954,-3.393],"ix":1}},{"ty":0,"nm":"Vertex Index","mn":"ADBE FreePin3 PosPin Vtx Index","ix":2,"v":{"a":0,"k":179,"ix":2}},{"ty":7,"nm":"Pin Type","mn":"ADBE FreePin3 PosPin Type","ix":3,"v":{"a":0,"k":1,"ix":3}},{"ty":3,"nm":"Position","mn":"ADBE FreePin3 PosPin Position","ix":4,"v":{"a":0,"k":[402,817.5],"ix":4}},{"ty":0,"nm":"Scale","mn":"ADBE FreePin3 PosPin Scale","ix":5,"v":{"a":0,"k":100,"ix":5}},{"ty":0,"nm":"Rotation","mn":"ADBE FreePin3 PosPin Rotation","ix":6,"v":{"a":0,"k":0,"ix":6}}]},{"nm":"Puppet Pin 1","np":7,"mn":"ADBE FreePin3 PosPin Atom","ix":5,"en":1,"ef":[{"ty":3,"nm":"Vertex Offset","mn":"ADBE FreePin3 PosPin Vtx Offset","ix":1,"v":{"a":0,"k":[5.312,22.562],"ix":1}},{"ty":0,"nm":"Vertex Index","mn":"ADBE FreePin3 PosPin Vtx Index","ix":2,"v":{"a":0,"k":222,"ix":2}},{"ty":7,"nm":"Pin Type","mn":"ADBE FreePin3 PosPin Type","ix":3,"v":{"a":0,"k":1,"ix":3}},{"ty":3,"nm":"Position","mn":"ADBE FreePin3 PosPin Position","ix":4,"v":{"a":1,"k":[{"i":{"x":0,"y":0},"o":{"x":0,"y":0},"t":0,"s":[335.5,720],"to":[0.75,-1.333],"ti":[0,0]},{"i":{"x":0,"y":0},"o":{"x":0,"y":0},"t":0,"s":[340,712],"to":[0,0],"ti":[0,0]},{"i":{"x":0,"y":0},"o":{"x":0,"y":0},"t":0,"s":[335.5,720],"to":[0,0],"ti":[0,0]},{"i":{"x":0,"y":0},"o":{"x":0,"y":0},"t":0,"s":[340,712],"to":[0,0],"ti":[0,0]},{"i":{"x":0,"y":0},"o":{"x":0,"y":0},"t":0,"s":[335.5,720],"to":[0,0],"ti":[0,0]},{"i":{"x":0,"y":0},"o":{"x":0,"y":0},"t":0,"s":[340,712],"to":[0,0],"ti":[0,0]},{"i":{"x":0,"y":0},"o":{"x":0,"y":0},"t":0,"s":[335.5,720],"to":[0,0],"ti":[0,0]},{"i":{"x":0,"y":0},"o":{"x":0,"y":0},"t":0,"s":[340,712],"to":[0,0],"ti":[0,0]},{"i":{"x":0,"y":0},"o":{"x":0,"y":0},"t":0,"s":[335.5,720],"to":[0,0],"ti":[0,0]},{"i":{"x":0,"y":0},"o":{"x":0,"y":0},"t":0,"s":[340,712],"to":[0,0],"ti":[0,0]},{"i":{"x":0,"y":0},"o":{"x":0,"y":0},"t":0,"s":[335.5,720],"to":[0,0],"ti":[0,0]},{"i":{"x":0,"y":0},"o":{"x":0,"y":0},"t":0,"s":[340,712],"to":[0,0],"ti":[0,0]},{"i":{"x":0,"y":0},"o":{"x":0,"y":0},"t":0,"s":[335.5,720],"to":[0,0],"ti":[0,0]},{"i":{"x":0,"y":0},"o":{"x":0,"y":0},"t":0,"s":[340,712],"to":[0,0],"ti":[0,0]},{"i":{"x":0,"y":0},"o":{"x":0,"y":0},"t":0,"s":[335.5,720],"to":[0,0],"ti":[0,0]},{"i":{"x":0,"y":0},"o":{"x":0,"y":0},"t":0,"s":[340,712],"to":[0,0],"ti":[0,0]},{"i":{"x":0,"y":0},"o":{"x":0,"y":0},"t":0,"s":[335.5,720],"to":[0,0],"ti":[0,0]},{"i":{"x":0,"y":0},"o":{"x":0,"y":0},"t":0,"s":[340,712],"to":[0,0],"ti":[0.75,-1.333]},{"t":null,"s":[335.5,720]}],"ix":4}},{"ty":0,"nm":"Scale","mn":"ADBE FreePin3 PosPin Scale","ix":5,"v":{"a":0,"k":100,"ix":5}},{"ty":0,"nm":"Rotation","mn":"ADBE FreePin3 PosPin Rotation","ix":6,"v":{"a":0,"k":0,"ix":6}}]}]},{"nm":"Overlap","np":1,"mn":"ADBE FreePin3 HghtPins","ix":5,"en":1,"ef":[]},{"nm":"Stiffness","np":1,"mn":"ADBE FreePin3 StarchPins","ix":6,"en":1,"ef":[]}]}]}]}]}],"sy":[{"c":{"a":0,"k":[0,0,0,1],"ix":2},"o":{"a":0,"k":75,"ix":3},"a":{"a":0,"k":120,"ix":5},"s":{"a":0,"k":5,"ix":8},"d":{"a":0,"k":5,"ix":6},"ch":{"a":0,"k":0,"ix":7},"bm":{"a":0,"k":5,"ix":1},"no":{"a":0,"k":0,"ix":9},"lc":{"a":0,"k":1,"ix":10},"ty":1,"nm":"Drop Shadow"},{"c":{"a":0,"k":[0,0,0,1],"ix":2},"o":{"a":0,"k":75,"ix":3},"a":{"a":0,"k":120,"ix":5},"s":{"a":0,"k":5,"ix":8},"d":{"a":0,"k":5,"ix":6},"ch":{"a":0,"k":0,"ix":7},"bm":{"a":0,"k":5,"ix":1},"no":{"a":0,"k":0,"ix":9},"ty":2,"nm":"Inner Shadow"},{"c":{"a":0,"k":[1,1,0.745098039216,1],"ix":5},"o":{"a":0,"k":75,"ix":2},"s":{"a":0,"k":5,"ix":10},"r":{"a":0,"k":50,"ix":11},"ch":{"a":0,"k":0,"ix":9},"bm":{"a":0,"k":11,"ix":1},"no":{"a":0,"k":0,"ix":3},"j":{"a":0,"k":0,"ix":12},"ty":3,"nm":"Outer Glow"},{"c":{"a":0,"k":[1,1,0.745098039216,1],"ix":5},"o":{"a":0,"k":75,"ix":2},"s":{"a":0,"k":5,"ix":11},"r":{"a":0,"k":50,"ix":12},"sr":{"a":0,"k":1,"ix":9},"ch":{"a":0,"k":0,"ix":10},"bm":{"a":0,"k":11,"ix":1},"no":{"a":0,"k":0,"ix":3},"j":{"a":0,"k":0,"ix":13},"ty":4,"nm":"Inner Glow"},{"c":{"a":0,"k":[1,0,0,1],"ix":2},"s":{"a":0,"k":3,"ix":3},"ty":0,"nm":"Stroke"}],"shapes":[{"ty":"gr","it":[{"ind":0,"ty":"sh","ix":1,"ks":{"a":0,"k":{"i":[[-1.605,27.274],[7.835,10.28],[-0.459,7.795],[13.361,0.786],[0.888,-15.094],[-3.069,-4.885],[1.175,-19.968],[-5.418,-10.133],[4.893,-3.228],[-2.119,-1.036],[0,0],[-0.022,0.042],[3.97,12.849]],"o":[[1.071,-18.202],[4.927,-4.707],[0.889,-15.095],[-13.361,-0.787],[-0.383,6.491],[-10.374,8.767],[-0.881,14.964],[-4.818,0.939],[4.19,13.771],[0,0],[0.022,-0.042],[9.214,-17.332],[16.229,-2.717]],"v":[[36.019,-3.243],[24.706,-48.135],[33.398,-67.493],[10.814,-96.248],[-14.987,-70.34],[-10.645,-52.89],[-29.831,-7.119],[-22.379,31.736],[-37.09,38.075],[-17.189,80.444],[-3.223,97.035],[-3.155,96.91],[4.529,48.562]],"c":true},"ix":2},"nm":"Path 1","mn":"ADBE Vector Shape - Group","hd":false},{"ty":"fl","c":{"a":0,"k":[0.910000011968,0.616000007181,0.375999989229,1],"ix":4},"o":{"a":0,"k":100,"ix":5},"r":1,"bm":0,"nm":"Fill 1","mn":"ADBE Vector Graphic - Fill","hd":false},{"ty":"tr","p":{"a":0,"k":[226.486,270.301],"ix":2},"a":{"a":0,"k":[0,0],"ix":1},"s":{"a":0,"k":[100,100],"ix":3},"r":{"a":0,"k":0,"ix":6},"o":{"a":0,"k":100,"ix":7},"sk":{"a":0,"k":0,"ix":4},"sa":{"a":0,"k":0,"ix":5},"nm":"Transform"}],"nm":"Group 1","np":4,"cix":2,"bm":0,"ix":1,"mn":"ADBE Vector Group","hd":false},{"ty":"gr","it":[{"ind":0,"ty":"sh","ix":1,"ks":{"a":0,"k":{"i":[[-0.755,-1.511],[0.458,-0.239],[12.395,69.146],[-35.99,9.948]],"o":[[-0.368,0.229],[-9.178,4.792],[0,0],[0.944,2.688]],"v":[[40.556,17.906],[39.307,18.614],[-40.556,-34.573],[38.003,11.562]],"c":true},"ix":2},"nm":"Path 1","mn":"ADBE Vector Shape - Group","hd":false},{"ty":"fl","c":{"a":0,"k":[0.8,0.513999968884,0.322000002394,1],"ix":4},"o":{"a":0,"k":100,"ix":5},"r":1,"bm":0,"nm":"Fill 1","mn":"ADBE Vector Graphic - Fill","hd":false},{"ty":"tr","p":{"a":0,"k":[519.438,258.185],"ix":2},"a":{"a":0,"k":[0,0],"ix":1},"s":{"a":0,"k":[100,100],"ix":3},"r":{"a":0,"k":0,"ix":6},"o":{"a":0,"k":100,"ix":7},"sk":{"a":0,"k":0,"ix":4},"sa":{"a":0,"k":0,"ix":5},"nm":"Transform"}],"nm":"Group 2","np":4,"cix":2,"bm":0,"ix":2,"mn":"ADBE Vector Group","hd":false},{"ty":"gr","it":[{"ind":0,"ty":"sh","ix":1,"ks":{"a":0,"k":{"i":[[0,0],[0,0],[3.264,9.788],[3.176,4.582],[5.159,2.73],[-0.624,1.181],[-1.18,-0.625],[-3.558,-5.27],[-1.553,-7.033],[-0.006,-0.097],[1.334,-0.065],[0.063,1.334]],"o":[[0,0],[-0.05,-0.908],[-1.629,-4.894],[-3.179,-4.586],[-1.18,-0.625],[0.624,-1.181],[6.17,3.264],[5.338,7.914],[1.548,7.035],[0.064,1.334],[-1.334,0.064],[0,0]],"v":[[10.062,23.991],[10.057,23.914],[6.152,4.495],[-0.948,-10.134],[-13.325,-21.454],[-14.331,-24.724],[-11.063,-25.732],[3.363,-12.399],[13.094,11.543],[14.891,23.761],[12.591,26.293],[10.062,23.992]],"c":true},"ix":2},"nm":"Path 1","mn":"ADBE Vector Shape - Group","hd":false},{"ty":"fl","c":{"a":0,"k":[0.204000001795,0.081999999402,0.136999990426,1],"ix":4},"o":{"a":0,"k":100,"ix":5},"r":1,"bm":0,"nm":"Fill 1","mn":"ADBE Vector Graphic - Fill","hd":false},{"ty":"tr","p":{"a":0,"k":[418.141,601.384],"ix":2},"a":{"a":0,"k":[0,0],"ix":1},"s":{"a":0,"k":[100,100],"ix":3},"r":{"a":0,"k":0,"ix":6},"o":{"a":0,"k":100,"ix":7},"sk":{"a":0,"k":0,"ix":4},"sa":{"a":0,"k":0,"ix":5},"nm":"Transform"}],"nm":"Group 3","np":4,"cix":2,"bm":0,"ix":3,"mn":"ADBE Vector Group","hd":false},{"ty":"gr","it":[{"ind":0,"ty":"sh","ix":1,"ks":{"a":0,"k":{"i":[[-0.044,1.336],[0,0],[-0.002,0.538],[2.261,9.479],[2.312,3.893],[3.722,1.668],[-0.546,1.219],[-1.219,-0.546],[-2.657,-4.484],[-1.066,-7.174],[0.01,-2.519],[0.001,-0.02],[1.335,0.044]],"o":[[0,0],[0.004,-0.132],[0.018,-3.136],[-1.125,-4.738],[-2.318,-3.904],[-1.218,-0.546],[0.546,-1.219],[4.879,2.189],[3.986,6.742],[1.058,7.174],[-0.004,0.769],[-0.043,1.336],[-1.334,-0.044]],"v":[[6.683,23.787],[6.685,23.727],[6.699,22.705],[4.272,0.588],[-0.812,-12.766],[-9.782,-21.367],[-10.999,-24.564],[-7.803,-25.783],[3.346,-15.236],[10.39,6.893],[11.535,22.725],[11.516,23.945],[9.02,26.285]],"c":true},"ix":2},"nm":"Path 1","mn":"ADBE Vector Shape - Group","hd":false},{"ty":"fl","c":{"a":0,"k":[0.204000001795,0.081999999402,0.136999990426,1],"ix":4},"o":{"a":0,"k":100,"ix":5},"r":1,"bm":0,"nm":"Fill 1","mn":"ADBE Vector Graphic - Fill","hd":false},{"ty":"tr","p":{"a":0,"k":[358.048,608.931],"ix":2},"a":{"a":0,"k":[0,0],"ix":1},"s":{"a":0,"k":[100,100],"ix":3},"r":{"a":0,"k":0,"ix":6},"o":{"a":0,"k":100,"ix":7},"sk":{"a":0,"k":0,"ix":4},"sa":{"a":0,"k":0,"ix":5},"nm":"Transform"}],"nm":"Group 4","np":4,"cix":2,"bm":0,"ix":4,"mn":"ADBE Vector Group","hd":false},{"ty":"gr","it":[{"ind":0,"ty":"sh","ix":1,"ks":{"a":0,"k":{"i":[[-65.677,-54.649],[-2.408,-13.601],[3.175,-16.048],[-7.685,-17.331],[-4.837,-22.26],[30.933,-14.693],[32.625,6.319],[0,0],[25.859,14.939],[0,0],[4.832,23.496],[1.218,3.712]],"o":[[0,0],[2.407,13.602],[-3.174,16.048],[7.686,17.331],[4.836,22.262],[0,0],[-14.64,-2.836],[0,0],[-25.86,-14.939],[0,0],[-4.831,-23.496],[-1.217,-3.712]],"v":[[12.627,-135.753],[-6.901,-77.767],[20.616,-17.106],[31.529,80.551],[67.521,117.772],[67.301,165.959],[24.86,177.307],[3.073,171.858],[-20.401,175.463],[-64.402,110.302],[-93.403,-60.844],[-93.06,-136.211]],"c":true},"ix":2},"nm":"Path 1","mn":"ADBE Vector Shape - Group","hd":false},{"ty":"fl","c":{"a":0,"k":[0.910000011968,0.616000007181,0.375999989229,1],"ix":4},"o":{"a":0,"k":100,"ix":5},"r":1,"bm":0,"nm":"Fill 1","mn":"ADBE Vector Graphic - Fill","hd":false},{"ty":"tr","p":{"a":0,"k":[364.075,460.939],"ix":2},"a":{"a":0,"k":[0,0],"ix":1},"s":{"a":0,"k":[100,100],"ix":3},"r":{"a":0,"k":0,"ix":6},"o":{"a":0,"k":100,"ix":7},"sk":{"a":0,"k":0,"ix":4},"sa":{"a":0,"k":0,"ix":5},"nm":"Transform"}],"nm":"Group 5","np":4,"cix":2,"bm":0,"ix":5,"mn":"ADBE Vector Group","hd":false},{"ty":"gr","it":[{"ind":0,"ty":"sh","ix":1,"ks":{"a":0,"k":{"i":[[-10.482,-30.021],[12.491,-14.676],[38.552,-8.166],[33.081,8.073],[20.494,13.416],[0,0],[0,0]],"o":[[-6.988,15.042],[-41.8,49.104],[-12.597,2.667],[-11.679,-2.854],[-4.093,-14.532],[0,0],[7.49,7.042]],"v":[[146.723,-32.185],[117.798,12.783],[25.424,89.621],[-81.276,74.803],[-139.809,45.898],[-146.723,21.533],[119.006,-92.288]],"c":true},"ix":2},"nm":"Path 1","mn":"ADBE Vector Shape - Group","hd":false},{"ty":"fl","c":{"a":0,"k":[0.8,0.513999968884,0.322000002394,1],"ix":4},"o":{"a":0,"k":100,"ix":5},"r":1,"bm":0,"nm":"Fill 1","mn":"ADBE Vector Graphic - Fill","hd":false},{"ty":"tr","p":{"a":0,"k":[344.16,92.539],"ix":2},"a":{"a":0,"k":[0,0],"ix":1},"s":{"a":0,"k":[100,100],"ix":3},"r":{"a":0,"k":0,"ix":6},"o":{"a":0,"k":100,"ix":7},"sk":{"a":0,"k":0,"ix":4},"sa":{"a":0,"k":0,"ix":5},"nm":"Transform"}],"nm":"Group 6","np":4,"cix":2,"bm":0,"ix":6,"mn":"ADBE Vector Group","hd":false},{"ty":"gr","it":[{"ind":0,"ty":"sh","ix":1,"ks":{"a":0,"k":{"i":[[0,0],[-6.68,-26.899],[0,0],[0,0]],"o":[[0,0],[6.681,26.899],[0,0],[0,0]],"v":[[-25.121,-68.902],[7.661,-37.67],[25.122,35.732],[-25.121,68.902]],"c":true},"ix":2},"nm":"Path 1","mn":"ADBE Vector Shape - Group","hd":false},{"ty":"fl","c":{"a":0,"k":[0.910000011968,0.616000007181,0.375999989229,1],"ix":4},"o":{"a":0,"k":100,"ix":5},"r":1,"bm":0,"nm":"Fill 1","mn":"ADBE Vector Graphic - Fill","hd":false},{"ty":"tr","p":{"a":0,"k":[516.004,149.619],"ix":2},"a":{"a":0,"k":[0,0],"ix":1},"s":{"a":0,"k":[100,100],"ix":3},"r":{"a":0,"k":0,"ix":6},"o":{"a":0,"k":100,"ix":7},"sk":{"a":0,"k":0,"ix":4},"sa":{"a":0,"k":0,"ix":5},"nm":"Transform"}],"nm":"Group 7","np":4,"cix":2,"bm":0,"ix":7,"mn":"ADBE Vector Group","hd":false},{"ty":"gr","it":[{"ind":0,"ty":"sh","ix":1,"ks":{"a":0,"k":{"i":[[17.155,3.723],[14.444,0.457],[0.984,5.513],[2.656,4.195],[-2.061,10.672],[2.939,16.471],[9.856,3.859],[0.019,0.058],[3.625,7.517],[10.261,-2.606],[-0.648,9.045],[0.053,-0.036],[2.415,-6.182],[-0.159,-8.769],[57.246,-2.861],[36.784,27.835],[15.778,15.221],[9.211,9.22],[0,0],[4.19,13.77],[6.496,-12.218],[-1.149,-11.809],[2.958,-11.424],[-5.886,-6.397],[2.385,-20.756],[-8.829,-10.388],[1.231,-4.754],[-12.957,-3.355],[-0.768,-0.109],[-2.622,-41.956],[-22.479,5.319],[-13.014,6.004],[-7.099,12.766],[0.591,15.426],[-31.352,4.256],[-17.156,17.552],[-11.24,-1.597],[-7.098,-1.065],[-12.423,3.192],[-21.296,7.447],[-17.154,7.447]],"o":[[-8.729,-1.895],[1.092,-4.923],[-0.968,-5.419],[3.675,-7.862],[12.17,-4.973],[-2.343,-13.123],[-0.018,-0.058],[2.15,-6.556],[-5.847,-12.127],[0.193,-2.076],[-0.052,0.035],[-1.029,6.522],[-6.972,3.666],[-25.4,41.084],[-48.346,2.416],[-17.705,-13.398],[-3.378,-3.259],[0,0],[-2.118,-1.035],[-9.091,5.999],[-7.399,13.918],[-9.934,1.402],[-2.552,9.857],[-11.53,7.748],[-2.3,20.013],[-2.94,3.356],[-3.79,14.639],[0.906,0.234],[-12.421,0.417],[0,0],[0,0],[0,0],[0,0],[0,0],[31.351,-4.255],[0,0],[11.239,1.595],[7.099,1.063],[12.422,-3.191],[0,0],[0,0]],"v":[[263.955,96.311],[223.939,93.029],[224.205,77.204],[218.62,62.665],[227.668,34.809],[244.084,-2.025],[223.746,-29.263],[223.69,-29.439],[221.717,-51.555],[193.629,-67.695],[195.061,-85.341],[194.9,-85.237],[189.712,-66.188],[179.11,-45.894],[65.93,24.226],[-67.531,-17.768],[-117.354,-62.601],[-139.151,-83.3],[-162.103,-116.483],[-182.003,-158.851],[-206.313,-130.982],[-215.59,-90.801],[-237.4,-69.896],[-231.524,-43.813],[-254.684,1.861],[-243.486,50.474],[-249.924,62.753],[-217.929,96.026],[-215.427,96.532],[-279.671,143.119],[-249.503,151.629],[-201.588,152.847],[-141.842,142.055],[-118.772,111.736],[-46.012,135.671],[64.015,113.864],[90.634,138.864],[140.323,143.651],[224.322,144.182],[256.857,140.991],[282.293,139.927]],"c":true},"ix":2},"nm":"Path 1","mn":"ADBE Vector Shape - Group","hd":false},{"ty":"fl","c":{"a":0,"k":[0.8,0.513999968884,0.322000002394,1],"ix":4},"o":{"a":0,"k":100,"ix":5},"r":1,"bm":0,"nm":"Fill 1","mn":"ADBE Vector Graphic - Fill","hd":false},{"ty":"tr","p":{"a":0,"k":[371.399,467.228],"ix":2},"a":{"a":0,"k":[0,0],"ix":1},"s":{"a":0,"k":[100,100],"ix":3},"r":{"a":0,"k":0,"ix":6},"o":{"a":0,"k":100,"ix":7},"sk":{"a":0,"k":0,"ix":4},"sa":{"a":0,"k":0,"ix":5},"nm":"Transform"}],"nm":"Group 8","np":4,"cix":2,"bm":0,"ix":8,"mn":"ADBE Vector Group","hd":false},{"ty":"gr","it":[{"ind":0,"ty":"sh","ix":1,"ks":{"a":0,"k":{"i":[[0,0],[0,0],[12.416,-3.188],[7.106,1.062],[11.24,1.603],[0,0],[31.35,-4.25],[0,0],[0,0],[0,0],[0,0],[0,0],[0,0],[0,0],[0,0],[1.304,17.02],[10.525,37.396],[0,0],[0,0],[-10.482,-30.021],[-13.218,-31.624],[-0.898,-1.511],[-0.385,-0.437],[0,0],[0,0],[0,0],[-17.16,-3.719]],"o":[[-17.15,7.437],[-21.296,7.449],[-12.427,3.187],[-7.094,-1.063],[-11.241,-1.594],[-17.161,17.562],[-31.361,4.26],[0.598,15.426],[-7.094,12.761],[-13.015,6],[-22.471,5.323],[-2.96,-47.343],[-18.432,-5.666],[-26.681,-123.758],[0,0],[-0.941,-12.26],[-4.092,-14.531],[0,0],[7.49,7.042],[24.426,69.936],[1.122,2.687],[0.449,0.77],[14.029,15.958],[28.389,15.959],[18.347,71.811],[0,0],[17.149,3.729]],"v":[[282.461,293.996],[257.03,295.058],[224.494,298.246],[140.487,297.715],[90.802,292.924],[64.185,267.924],[-45.84,289.736],[-118.605,265.799],[-141.674,296.121],[-201.415,306.913],[-249.338,305.694],[-279.502,297.184],[-212.752,250.549],[-239.935,211.184],[-173.794,73.249],[-136.471,-56.53],[-166.881,-174.727],[-173.794,-199.091],[91.935,-312.913],[119.651,-252.809],[185.729,-43.416],[188.763,-37.072],[190.014,-35.26],[193.732,87.082],[225.669,132.29],[198.465,246.653],[264.125,250.372]],"c":true},"ix":2},"nm":"Path 1","mn":"ADBE Vector Shape - Group","hd":false},{"ty":"fl","c":{"a":0,"k":[0.910000011968,0.616000007181,0.375999989229,1],"ix":4},"o":{"a":0,"k":100,"ix":5},"r":1,"bm":0,"nm":"Fill 1","mn":"ADBE Vector Graphic - Fill","hd":false},{"ty":"tr","p":{"a":0,"k":[371.231,313.163],"ix":2},"a":{"a":0,"k":[0,0],"ix":1},"s":{"a":0,"k":[100,100],"ix":3},"r":{"a":0,"k":0,"ix":6},"o":{"a":0,"k":100,"ix":7},"sk":{"a":0,"k":0,"ix":4},"sa":{"a":0,"k":0,"ix":5},"nm":"Transform"}],"nm":"Group 9","np":4,"cix":2,"bm":0,"ix":9,"mn":"ADBE Vector Group","hd":false},{"ty":"gr","it":[{"ind":0,"ty":"sh","ix":1,"ks":{"a":0,"k":{"i":[[-14.827,-4.156],[-4.356,-4.179],[-0.973,-7.196],[-0.552,-1.693],[3.837,-20.423],[-12.264,-8.98],[2.17,1.704],[-2.872,15.286],[4.842,10.991],[1.441,10.649],[4.356,4.179],[0.974,7.197],[7.304,3.758],[1.463,10.829],[14.679,4.37],[1.355,10.022],[10.916,1.119],[0.91,6.726],[13.264,-1.794],[-2.026,-14.984],[-11.354,-0.971],[-0.866,-6.411],[-9.142,-2.741],[-3.128,-23.139]],"o":[[0.919,6.787],[-3.483,5.327],[0.249,1.842],[-11.971,6.971],[-4.544,24.186],[5.922,-3.615],[8.117,-8.516],[2.969,-15.8],[7.463,-5.279],[-0.918,-6.79],[3.483,-5.326],[-1.286,-9.513],[2.226,-8.884],[-3.337,-24.674],[6.669,-5.47],[-1.718,-12.704],[2.946,-5.226],[-2.027,-14.984],[-13.264,1.794],[1.783,13.173],[-2.739,5.033],[1.505,11.127],[-11.505,9.205],[3.365,24.878]],"v":[[2.061,28.693],[10.439,45.541],[6.263,64.93],[7.474,70.24],[-18.687,114.038],[-4.946,169.447],[28.653,160.768],[46.143,126.217],[42.728,84.452],[53.083,58.598],[44.705,41.745],[48.88,22.355],[34.714,1.349],[36.078,-28.699],[5.087,-77.136],[14.158,-102.016],[-7.841,-125.374],[-4.465,-143.77],[-32.151,-167.653],[-52.498,-137.274],[-29.566,-113.277],[-32.664,-95.684],[-14.645,-73.125],[-29.292,-19.858]],"c":true},"ix":2},"nm":"Path 1","mn":"ADBE Vector Shape - Group","hd":false},{"ty":"fl","c":{"a":0,"k":[0.910000011968,0.616000007181,0.375999989229,1],"ix":4},"o":{"a":0,"k":100,"ix":5},"r":1,"bm":0,"nm":"Fill 1","mn":"ADBE Vector Graphic - Fill","hd":false},{"ty":"tr","p":{"a":0,"k":[537.808,221.119],"ix":2},"a":{"a":0,"k":[0,0],"ix":1},"s":{"a":0,"k":[100,100],"ix":3},"r":{"a":0,"k":0,"ix":6},"o":{"a":0,"k":100,"ix":7},"sk":{"a":0,"k":0,"ix":4},"sa":{"a":0,"k":0,"ix":5},"nm":"Transform"}],"nm":"Group 10","np":4,"cix":2,"bm":0,"ix":10,"mn":"ADBE Vector Group","hd":false},{"ty":"gr","it":[{"ind":0,"ty":"sh","ix":1,"ks":{"a":0,"k":{"i":[[-64.27,90.302],[73.992,-28.654],[36.66,-62.437],[-35.847,-11.23],[-45.685,-23.04],[0,0],[-3.747,-13.91]],"o":[[0,0],[0,0],[0,0],[0,0],[0,0],[0,0],[3.747,13.909]],"v":[[101.654,40.483],[16.039,-55.806],[-60.098,-68.348],[-50.377,-6.7],[-55.969,28.776],[-4.113,42.35],[-36.004,65.401]],"c":true},"ix":2},"nm":"Path 1","mn":"ADBE Vector Shape - Group","hd":false},{"ty":"fl","c":{"a":0,"k":[0.8,0.513999968884,0.322000002394,1],"ix":4},"o":{"a":0,"k":100,"ix":5},"r":1,"bm":0,"nm":"Fill 1","mn":"ADBE Vector Graphic - Fill","hd":false},{"ty":"tr","p":{"a":0,"k":[101.904,328.694],"ix":2},"a":{"a":0,"k":[0,0],"ix":1},"s":{"a":0,"k":[100,100],"ix":3},"r":{"a":0,"k":0,"ix":6},"o":{"a":0,"k":100,"ix":7},"sk":{"a":0,"k":0,"ix":4},"sa":{"a":0,"k":0,"ix":5},"nm":"Transform"}],"nm":"Group 11","np":4,"cix":2,"bm":0,"ix":11,"mn":"ADBE Vector Group","hd":false}],"ip":0,"op":150.000006109625,"st":0,"bm":0}],"markers":[]}